LabTest/test2018.v
/*
NAME: ANIRUDH SRINIVASAN CHAKRAVARTHY
ID: 2017A7PS1195P
*/

module tff(t, clk, reset, q);
	input t, clk, reset; // active low reset pin
	output reg q;
	always @(posedge clk) begin
		if (!reset) q <= 0;
		else q <= t ^ q;
	end
endmodule

module d_ff(d, clk, reset, q);
	input d, clk, reset;
	output reg q;
	always @(posedge clk) begin
		if (!reset) q <= 0;
		else q <= d;
	end
endmodule

module counter_4bit(clk, reset, q);
	input clk, reset;
	output[3:0] q;

	tff ta(1'b1, clk, reset, q[0]);
	tff tb(q[0], clk, reset, q[1]);

	wire t2;
	assign t2 = q[0] & q[1];
	tff tc(t2, clk, reset, q[2]);

	wire t3;
	assign t3 = t2 & q[2];
	tff td(t3, clk, reset, q[3]);
endmodule

module ControlLogic(s, z, x, clk, t0, t1, t2);
	input s, z, x, clk;
	output t0, t1, t2;
	wire da, db, dc; // input to flip-flops

	assign t0 = 1'b1; // WRONG but can't figure out what else to do

	wire nots, notx ,notz;
	not ns(nots, s);
	not nx(notx, x);
	not nz(notz, z);

	// for first d flipflop
	wire p1, p2;
	and a0(p1, t0, nots);
	and a1(p2, t2, z);
	or o0(da, p1, p2);
	d_ff d0(da, clk, s, t0);

	// second d flipflop
	wire q1, q2, q3;
	and a2(q1, t0, s);
	and a3(q2, t2, notx, notz);
	and a4(q3, t1, notx);
	or o1(db, q1, q2, q3);
	d_ff d1(db, clk, s, t1);

	// third d flipflop
	wire r1, r2;
	and a5(r1, t1, x);
	and a6(r2, t2, notz, x);
	or o2(dc, r1, r2);
	d_ff d2(dc, clk, s, t2);
endmodule

module intg(s, clk, x, q, g);
	input s, clk, x;
	output g;
	output[3:0] q; // counter values
	wire t0, t1, t2;

	// for counter
	wire en, reset;
	wire counterclk; // for clock-gating
	assign en = (t1 & x) | (t2 & ~z & x);
	assign reset = t0 & s;
	assign counterclk = clk & en;
	counter_4bit c0(counterclk, reset, q);

	// for controller
	wire z; 
	assign z = q[3] & q[2] & q[1] & q[0];
	ControlLogic cl0(s, z, x, clk, t0, t1, t2);

	// for dff
	wire dg;
	assign dg = z & t2;
	d_ff df0(dg, clk, s, g);
endmodule
	
/* NOTE: counter Testbench - WORKING */
// module tb_counter;
// 	reg clk, reset;
// 	wire[3:0] q;
// 	wire g;
// 	counter_4bit c0(clk, reset, q);

// 	always #500000 clk = ~clk;

// 	initial begin
// 		$monitor(,$time," q=%4b", q);
// 		clk = 1'b0; reset = 1'b0; 
// 		#1000000 reset = 1'b1;
// 		#19000000 $finish;
// 	end 
// endmodule

module tb_g;
	reg clk, s, x;
	wire[3:0] q;
	wire g;
	intg ig0(s, clk, x, q, g);

	always #500000 clk = ~clk;

	initial begin
		clk = 1'b0; s = 1'b0;
		$monitor(,$time," q=%4b, g=%b", q, g);
		#1000000 s = 1'b1; x = 1'b1;
		#19000000 $finish;
	end

	initial begin
		$dumpfile("test.vcd");
		$dumpvars;
	end
endmodule

LabTest/test.vcd
$date
	Sat Nov  9 23:05:26 2019
$end
$version
	Icarus Verilog
$end
$timescale
	1s
$end
$scope module tb_g $end
$var wire 4 ! q [3:0] $end
$var wire 1 " g $end
$var reg 1 # clk $end
$var reg 1 $ s $end
$var reg 1 % x $end
$scope module ig0 $end
$var wire 1 # clk $end
$var wire 1 & counterclk $end
$var wire 1 ' dg $end
$var wire 1 ( en $end
$var wire 1 ) reset $end
$var wire 1 $ s $end
$var wire 1 * t0 $end
$var wire 1 % x $end
$var wire 1 + z $end
$var wire 1 , t2 $end
$var wire 1 - t1 $end
$var wire 4 . q [3:0] $end
$var wire 1 " g $end
$scope module c0 $end
$var wire 1 & clk $end
$var wire 1 ) reset $end
$var wire 1 / t2 $end
$var wire 1 0 t3 $end
$var wire 4 1 q [3:0] $end
$scope module ta $end
$var wire 1 & clk $end
$var wire 1 ) reset $end
$var wire 1 2 t $end
$var reg 1 3 q $end
$upscope $end
$scope module tb $end
$var wire 1 & clk $end
$var wire 1 ) reset $end
$var wire 1 4 t $end
$var reg 1 5 q $end
$upscope $end
$scope module tc $end
$var wire 1 & clk $end
$var wire 1 ) reset $end
$var wire 1 / t $end
$var reg 1 6 q $end
$upscope $end
$scope module td $end
$var wire 1 & clk $end
$var wire 1 ) reset $end
$var wire 1 0 t $end
$var reg 1 7 q $end
$upscope $end
$upscope $end
$scope module cl0 $end
$var wire 1 # clk $end
$var wire 1 8 da $end
$var wire 1 9 db $end
$var wire 1 : dc $end
$var wire 1 ; nots $end
$var wire 1 < notx $end
$var wire 1 = notz $end
$var wire 1 > p1 $end
$var wire 1 ? p2 $end
$var wire 1 @ q1 $end
$var wire 1 A q2 $end
$var wire 1 B q3 $end
$var wire 1 C r1 $end
$var wire 1 D r2 $end
$var wire 1 $ s $end
$var wire 1 * t0 $end
$var wire 1 % x $end
$var wire 1 + z $end
$var wire 1 , t2 $end
$var wire 1 - t1 $end
$scope module d0 $end
$var wire 1 # clk $end
$var wire 1 8 d $end
$var wire 1 $ reset $end
$var reg 1 E q $end
$upscope $end
$scope module d1 $end
$var wire 1 # clk $end
$var wire 1 9 d $end
$var wire 1 $ reset $end
$var reg 1 - q $end
$upscope $end
$scope module d2 $end
$var wire 1 # clk $end
$var wire 1 : d $end
$var wire 1 $ reset $end
$var reg 1 , q $end
$upscope $end
$upscope $end
$scope module df0 $end
$var wire 1 # clk $end
$var wire 1 ' d $end
$var wire 1 $ reset $end
$var reg 1 " q $end
$upscope $end
$upscope $end
$upscope $end
$enddefinitions $end
#0
$dumpvars
xE
xD
xC
xB
xA
0@
x?
x>
x=
x<
1;
x:
x9
x8
x7
x6
x5
x4
x3
12
bx 1
x0
x/
bx .
x-
x,
x+
x*
0)
x(
x'
0&
x%
0$
0#
x"
bx !
$end
#500000
1=
0+
0/
00
0(
0:
09
04
0C
0B
0D
0A
0?
0'
03
05
06
b0 !
b0 .
b0 1
07
0E
0-
0,
0"
0&
1#
#1000000
08
0>
x9
0<
x)
0;
x@
0#
1%
1$
#1500000
14
b1 !
b1 .
b1 1
13
x&
x:
x(
xC
x-
1#
#2000000
0&
0#
#2500000
04
xD
03
b10 !
b10 .
b10 1
15
x,
x&
1#
#3000000
0&
0#
#3500000
1/
14
b11 !
b11 .
b11 1
13
x&
1#
#4000000
0&
0#
#4500000
0/
00
04
03
05
b100 !
b100 .
b100 1
16
x&
1#
#5000000
0&
0#
#5500000
14
b101 !
b101 .
b101 1
13
x&
1#
#6000000
0&
0#
#6500000
04
03
b110 !
b110 .
b110 1
15
x&
1#
#7000000
0&
0#
#7500000
10
1/
14
b111 !
b111 .
b111 1
13
x&
1#
#8000000
0&
0#
#8500000
0/
00
04
03
05
06
b1000 !
b1000 .
b1000 1
17
x&
1#
#9000000
0&
0#
#9500000
14
b1001 !
b1001 .
b1001 1
13
x&
1#
#10000000
0&
0#
#10500000
04
03
b1010 !
b1010 .
b1010 1
15
x&
1#
#11000000
0&
0#
#11500000
1/
14
b1011 !
b1011 .
b1011 1
13
x&
1#
#12000000
0&
0#
#12500000
0/
00
04
03
05
b1100 !
b1100 .
b1100 1
16
x&
1#
#13000000
0&
0#
#13500000
14
b1101 !
b1101 .
b1101 1
13
x&
1#
#14000000
0&
0#
#14500000
04
03
b1110 !
b1110 .
b1110 1
15
x&
1#
#15000000
0&
0#
#15500000
0D
x8
10
x'
0=
x?
1/
1+
14
b1111 !
b1111 .
b1111 1
13
x&
1#
#16000000
0&
0#
#16500000
xD
08
0'
1=
0?
0+
0/
00
04
03
05
06
b0 !
b0 .
b0 1
07
xE
x"
x&
1#
#17000000
0&
0#
#17500000
14
b1 !
b1 .
b1 1
13
0"
0E
x&
1#
#18000000
0&
0#
#18500000
04
03
b10 !
b10 .
b10 1
15
x&
1#
#19000000
0&
0#
#19500000
1/
14
b11 !
b11 .
b11 1
13
x&
1#
