Lab3/counter.v
module jkff(j,k,clk,en,q);
	input j,k,clk,en;
	output q;
	reg q;

	always @ (posedge clk) begin
		if (!en) q <= 1'b0;
		else q <= (j & ~q) | (~k & q);
	end
endmodule

// jk flip flip testing
// module testbench;
// 	reg j,k,clk,en;
// 	wire q;
// 	jkff j0(j,k,clk,en,q);

// 	always #5 clk = ~clk;

// 	initial begin
// 		$monitor(,$time," j=%b, k=%b, clk=%b, q=%b",j,k,clk,q);
// 		en=1'b0; clk=1'b0;
// 		#12 en=1'b1; j=1'b0; k=1'b0; 
// 		#12 j=1'b0; k=1'b1;
// 		#12 j=1'b1;
// 		#12 k=1'b0;
// 		#12 $finish;
// 	end
// endmodule

module synccounter(clk,en,q);
	input clk,en;
	output[3:0] q;
	wire p0,p1;
	
	jkff j0(1'b1,1'b1,clk,en,q[0]);
	jkff j1(q[0],q[0],clk,en,q[1]);
	
	and a0(p0, q[0],q[1]);
	jkff j2(p0,p0,clk,en,q[2]);

	and a1(p1,p0,q[2]);
	jkff j3(p1,p1,clk,en,q[3]);
endmodule

module testbench;
	reg clk,en;
	wire[3:0] q;
	synccounter c(clk,en,q);

	always #5 clk = ~clk;

	initial begin
		$monitor(,$time," clk=%b, q=%4b",clk,q);
		clk=0; en=0;
		#12 en=1;
	end

	initial begin
		$dumpfile("counter.vcd");
		$dumpvars;
	end
endmodule

Lab3/counter.vcd
$date
	Sat Nov  9 10:46:14 2019
$end
$version
	Icarus Verilog
$end
$timescale
	1s
$end
$scope module testbench $end
$var wire 4 ! q [3:0] $end
$var reg 1 " clk $end
$var reg 1 # en $end
$scope module c $end
$var wire 1 " clk $end
$var wire 1 # en $end
$var wire 1 $ p0 $end
$var wire 1 % p1 $end
$var wire 4 & q [3:0] $end
$scope module j0 $end
$var wire 1 " clk $end
$var wire 1 # en $end
$var wire 1 ' j $end
$var wire 1 ( k $end
$var reg 1 ) q $end
$upscope $end
$scope module j1 $end
$var wire 1 " clk $end
$var wire 1 # en $end
$var wire 1 * j $end
$var wire 1 + k $end
$var reg 1 , q $end
$upscope $end
$scope module j2 $end
$var wire 1 " clk $end
$var wire 1 # en $end
$var wire 1 $ j $end
$var wire 1 $ k $end
$var reg 1 - q $end
$upscope $end
$scope module j3 $end
$var wire 1 " clk $end
$var wire 1 # en $end
$var wire 1 % j $end
$var wire 1 % k $end
$var reg 1 . q $end
$upscope $end
$upscope $end
$upscope $end
$enddefinitions $end
#0
$dumpvars
x.
x-
x,
x+
x*
x)
1(
1'
bx &
x%
x$
0#
0"
bx !
$end
#5
0$
0%
0+
0*
0)
0,
0-
b0 !
b0 &
0.
1"
#10
0"
#12
1#
#15
1+
1*
b1 !
b1 &
1)
1"
#20
0"
#25
0+
0*
0)
b10 !
b10 &
1,
1"
#30
0"
#35
1$
1+
1*
b11 !
b11 &
1)
1"
#40
0"
#45
0$
0%
0+
0*
0)
0,
b100 !
b100 &
1-
1"
#50
0"
#55
1+
1*
b101 !
b101 &
1)
1"
#60
0"
#65
0+
0*
0)
b110 !
b110 &
1,
1"
#70
0"
#75
1%
1$
1+
1*
b111 !
b111 &
1)
1"
#80
0"
#85
0$
0%
0+
0*
0)
0,
0-
b1000 !
b1000 &
1.
1"
#90
0"
#95
1+
1*
b1001 !
b1001 &
1)
1"
#100
0"
#105
0+
0*
0)
b1010 !
b1010 &
1,
1"
#110
0"
#115
1$
1+
1*
b1011 !
b1011 &
1)
1"
#120
0"
#125
0$
0%
0+
0*
0)
0,
b1100 !
b1100 &
1-
1"
#130
0"
#135
1+
1*
b1101 !
b1101 &
1)
1"
#140
0"
#145
0+
0*
0)
b1110 !
b1110 &
1,
1"
#150
0"
#155
1%
1$
1+
1*
b1111 !
b1111 &
1)
1"
#160
0"
#165
0$
0%
0+
0*
0)
0,
0-
b0 !
b0 &
0.
1"
#170
0"
#175
1+
1*
b1 !
b1 &
1)
1"
#180
0"
#185
0+
0*
0)
b10 !
b10 &
1,
1"
#190
0"
#195
1$
1+
1*
b11 !
b11 &
1)
1"
#200
0"
#205
0$
0%
0+
0*
0)
0,
b100 !
b100 &
1-
1"
#210
0"
#215
1+
1*
b101 !
b101 &
1)
1"
#220
0"
#225
0+
0*
0)
b110 !
b110 &
1,
1"
#230
0"
#235
1%
1$
1+
1*
b111 !
b111 &
1)
1"
#240
0"
#245
0$
0%
0+
0*
0)
0,
0-
b1000 !
b1000 &
1.
1"
#250
0"
#255
1+
1*
b1001 !
b1001 &
1)
1"
#260
0"
#265
0+
0*
0)
b1010 !
b1010 &
1,
1"
#270
0"
#275
1$
1+
1*
b1011 !
b1011 &
1)
1"
#280
0"
#285
0$
0%
0+
0*
0)
0,
b1100 !
b1100 &
1-
1"
#290
0"
#295
1+
1*
b1101 !
b1101 &
1)
1"
#300
0"
#305
0+
0*
0)
b1110 !
b1110 &
1,
1"
#310
0"
#315
1%
1$
1+
1*
b1111 !
b1111 &
1)
1"
#320
0"
#325
0$
0%
0+
0*
0)
0,
0-
b0 !
b0 &
0.
1"
#330
0"
#335
1+
1*
b1 !
b1 &
1)
1"
#340
0"
#345
0+
0*
0)
b10 !
b10 &
1,
1"
#350
0"
#355
1$
1+
1*
b11 !
b11 &
1)
1"
#360
0"
#365
0$
0%
0+
0*
0)
0,
b100 !
b100 &
1-
1"
#370
0"
#375
1+
1*
b101 !
b101 &
1)
1"
#380
0"
#385
0+
0*
0)
b110 !
b110 &
1,
1"
#390
0"
#395
1%
1$
1+
1*
b111 !
b111 &
1)
1"
#400
0"
#405
0$
0%
0+
0*
0)
0,
0-
b1000 !
b1000 &
1.
1"
#410
0"
#415
1+
1*
b1001 !
b1001 &
1)
1"
#420
0"
#425
0+
0*
0)
b1010 !
b1010 &
1,
1"
#430
0"
#435
1$
1+
1*
b1011 !
b1011 &
1)
1"
#440
0"
#445
0$
0%
0+
0*
0)
0,
b1100 !
b1100 &
1-
1"
#450
0"
#455
1+
1*
b1101 !
b1101 &
1)
1"
#460
0"
#465
0+
0*
0)
b1110 !
b1110 &
1,
1"
#470
0"
#475
1%
1$
1+
1*
b1111 !
b1111 &
1)
1"
#480
0"
#485
0$
0%
0+
0*
0)
0,
0-
b0 !
b0 &
0.
1"
#490
0"
#495
1+
1*
b1 !
b1 &
1)
1"
#500
0"
#505
0+
0*
0)
b10 !
b10 &
1,
1"
#510
0"
#515
1$
1+
1*
b11 !
b11 &
1)
1"
#520
0"
#525
0$
0%
0+
0*
0)
0,
b100 !
b100 &
1-
1"
#530
0"
#535
1+
1*
b101 !
b101 &
1)
1"
#540
0"
#545
0+
0*
0)
b110 !
b110 &
1,
1"
#550
0"
#555
1%
1$
1+
1*
b111 !
b111 &
1)
1"
#560
0"
#565
0$
0%
0+
0*
0)
0,
0-
b1000 !
b1000 &
1.
1"
#570
0"
#575
1+
1*
b1001 !
b1001 &
1)
1"
#580
0"
#585
0+
0*
0)
b1010 !
b1010 &
1,
1"
#590
0"
#595
1$
1+
1*
b1011 !
b1011 &
1)
1"
#600
0"
#605
0$
0%
0+
0*
0)
0,
b1100 !
b1100 &
1-
1"
#610
0"
#615
1+
1*
b1101 !
b1101 &
1)
1"
#620
0"
#625
0+
0*
0)
b1110 !
b1110 &
1,
1"
#630
0"
#635
1%
1$
1+
1*
b1111 !
b1111 &
1)
1"
#640
0"
#645
0$
0%
0+
0*
0)
0,
0-
b0 !
b0 &
0.
1"
#650
0"
#655
1+
1*
b1 !
b1 &
1)
1"
#660
0"
#665
0+
0*
0)
b10 !
b10 &
1,
1"
#670
0"
#675
1$
1+
1*
b11 !
b11 &
1)
1"
#680
0"
#685
0$
0%
0+
0*
0)
0,
b100 !
b100 &
1-
1"
#690
0"
#695
1+
1*
b101 !
b101 &
1)
1"
#700
0"
#705
0+
0*
0)
b110 !
b110 &
1,
1"
#710
0"
#715
1%
1$
1+
1*
b111 !
b111 &
1)
1"
#720
0"
#725
0$
0%
0+
0*
0)
0,
0-
b1000 !
b1000 &
1.
1"
#730
0"
#735
1+
1*
b1001 !
b1001 &
1)
1"
#740
0"
#745
0+
0*
0)
b1010 !
b1010 &
1,
1"
#750
0"
#755
1$
1+
1*
b1011 !
b1011 &
1)
1"
#760
0"
#765
0$
0%
0+
0*
0)
0,
b1100 !
b1100 &
1-
1"
#770
0"
#775
1+
1*
b1101 !
b1101 &
1)
1"
#780
0"
#785
0+
0*
0)
b1110 !
b1110 &
1,
1"
#790
0"
#795
1%
1$
1+
1*
b1111 !
b1111 &
1)
1"
#800
0"
#805
0$
0%
0+
0*
0)
0,
0-
b0 !
b0 &
0.
1"
#810
0"
#815
1+
1*
b1 !
b1 &
1)
1"
#820
0"
#825
0+
0*
0)
b10 !
b10 &
1,
1"
#830
0"
#835
1$
1+
1*
b11 !
b11 &
1)
1"
#840
0"
#845
0$
0%
0+
0*
0)
0,
b100 !
b100 &
1-
1"
#850
0"
#855
1+
1*
b101 !
b101 &
1)
1"
#860
0"
#865
0+
0*
0)
b110 !
b110 &
1,
1"
#870
0"
#875
1%
1$
1+
1*
b111 !
b111 &
1)
1"
#880
0"
#885
0$
0%
0+
0*
0)
0,
0-
b1000 !
b1000 &
1.
1"
#890
0"
#895
1+
1*
b1001 !
b1001 &
1)
1"
#900
0"
#905
0+
0*
0)
b1010 !
b1010 &
1,
1"
#910
0"
#915
1$
1+
1*
b1011 !
b1011 &
1)
1"
#920
0"
#925
0$
0%
0+
0*
0)
0,
b1100 !
b1100 &
1-
1"
#930
0"
#935
1+
1*
b1101 !
b1101 &
1)
1"
#940
0"
#945
0+
0*
0)
b1110 !
b1110 &
1,
1"
#950
0"
#955
1%
1$
1+
1*
b1111 !
b1111 &
1)
1"
#960
0"
#965
0$
0%
0+
0*
0)
0,
0-
b0 !
b0 &
0.
1"
#970
0"
#975
1+
1*
b1 !
b1 &
1)
1"
#980
0"
#985
0+
0*
0)
b10 !
b10 &
1,
1"
#990
0"
#995
1$
1+
1*
b11 !
b11 &
1)
1"
#1000
0"
#1005
0$
0%
0+
0*
0)
0,
b100 !
b100 &
1-
1"
#1010
0"
#1015
1+
1*
b101 !
b101 &
1)
1"
#1020
0"
#1025
0+
0*
0)
b110 !
b110 &
1,
1"
#1030
0"
#1035
1%
1$
1+
1*
b111 !
b111 &
1)
1"
#1040
0"
#1045
0$
0%
0+
0*
0)
0,
0-
b1000 !
b1000 &
1.
1"
#1050
0"
#1055
1+
1*
b1001 !
b1001 &
1)
1"
#1060
0"
#1065
0+
0*
0)
b1010 !
b1010 &
1,
1"
#1070
0"
#1075
1$
1+
1*
b1011 !
b1011 &
1)
1"
#1080
0"
#1085
0$
0%
0+
0*
0)
0,
b1100 !
b1100 &
1-
1"
#1090
0"
#1095
1+
1*
b1101 !
b1101 &
1)
1"
#1100
0"
#1105
0+
0*
0)
b1110 !
b1110 &
1,
1"
#1110
0"
#1115
1%
1$
1+
1*
b1111 !
b1111 &
1)
1"
#1120
0"
#1125
0$
0%
0+
0*
0)
0,
0-
b0 !
b0 &
0.
1"
#1130
0"
#1135
1+
1*
b1 !
b1 &
1)
1"
#1140
0"
#1145
0+
0*
0)
b10 !
b10 &
1,
1"
#1150
0"
#1155
1$
1+
1*
b11 !
b11 &
1)
1"
#1160
0"
#1165
0$
0%
0+
0*
0)
0,
b100 !
b100 &
1-
1"
#1170
0"
#1175
1+
1*
b101 !
b101 &
1)
1"
#1180
0"
#1185
0+
0*
0)
b110 !
b110 &
1,
1"
#1190
0"
#1195
1%
1$
1+
1*
b111 !
b111 &
1)
1"
#1200
0"
#1205
0$
0%
0+
0*
0)
0,
0-
b1000 !
b1000 &
1.
1"
#1210
0"
#1215
1+
1*
b1001 !
b1001 &
1)
1"
#1220
0"
#1225
0+
0*
0)
b1010 !
b1010 &
1,
1"
#1230
0"
#1235
1$
1+
1*
b1011 !
b1011 &
1)
1"
#1240
0"
#1245
0$
0%
0+
0*
0)
0,
b1100 !
b1100 &
1-
1"
#1250
0"
#1255
1+
1*
b1101 !
b1101 &
1)
1"
#1260
0"
#1265
0+
0*
0)
b1110 !
b1110 &
1,
1"
#1270
0"
#1275
1%
1$
1+
1*
b1111 !
b1111 &
1)
1"
#1280
0"
#1285
0$
0%
0+
0*
0)
0,
0-
b0 !
b0 &
0.
1"
#1290
0"
#1295
1+
1*
b1 !
b1 &
1)
1"
#1300
0"
#1305
0+
0*
0)
b10 !
b10 &
1,
1"
#1310
0"
#1315
1$
1+
1*
b11 !
b11 &
1)
1"
#1320
0"
#1325
0$
0%
0+
0*
0)
0,
b100 !
b100 &
1-
1"
#1330
0"
#1335
1+
1*
b101 !
b101 &
1)
1"
#1340
0"
#1345
0+
0*
0)
b110 !
b110 &
1,
1"
#1350
0"
#1355
1%
1$
1+
1*
b111 !
b111 &
1)
1"
#1360
0"
#1365
0$
0%
0+
0*
0)
0,
0-
b1000 !
b1000 &
1.
1"
#1370
0"
#1375
1+
1*
b1001 !
b1001 &
1)
1"
#1380
0"
#1385
0+
0*
0)
b1010 !
b1010 &
1,
1"
#1390
0"
#1395
1$
1+
1*
b1011 !
b1011 &
1)
1"
#1400
0"
#1405
0$
0%
0+
0*
0)
0,
b1100 !
b1100 &
1-
1"
#1410
0"
#1415
1+
1*
b1101 !
b1101 &
1)
1"
#1420
0"
#1425
0+
0*
0)
b1110 !
b1110 &
1,
1"
#1430
0"
#1435
1%
1$
1+
1*
b1111 !
b1111 &
1)
1"
#1440
0"
#1445
0$
0%
0+
0*
0)
0,
0-
b0 !
b0 &
0.
1"
#1450
0"
#1455
1+
1*
b1 !
b1 &
1)
1"
#1460
0"
#1465
0+
0*
0)
b10 !
b10 &
1,
1"
#1470
0"
#1475
1$
1+
1*
b11 !
b11 &
1)
1"
#1480
0"
#1485
0$
0%
0+
0*
0)
0,
b100 !
b100 &
1-
1"
#1490
0"
#1495
1+
1*
b101 !
b101 &
1)
1"
#1500
0"
#1505
0+
0*
0)
b110 !
b110 &
1,
1"
#1510
0"
#1515
1%
1$
1+
1*
b111 !
b111 &
1)
1"
#1520
0"
#1525
0$
0%
0+
0*
0)
0,
0-
b1000 !
b1000 &
1.
1"
#1530
0"
#1535
1+
1*
b1001 !
b1001 &
1)
1"
#1540
0"
#1545
0+
0*
0)
b1010 !
b1010 &
1,
1"
#1550
0"
#1555
1$
1+
1*
b1011 !
b1011 &
1)
1"
#1560
0"
#1565
0$
0%
0+
0*
0)
0,
b1100 !
b1100 &
1-
1"
#1570
0"
#1575
1+
1*
b1101 !
b1101 &
1)
1"
#1580
0"
#1585
0+
0*
0)
b1110 !
b1110 &
1,
1"
#1590
0"
#1595
1%
1$
1+
1*
b1111 !
b1111 &
1)
1"
#1600
0"
#1605
0$
0%
0+
0*
0)
0,
0-
b0 !
b0 &
0.
1"
#1610
0"
#1615
1+
1*
b1 !
b1 &
1)
1"
#1620
0"
#1625
0+
0*
0)
b10 !
b10 &
1,
1"
#1630
0"
#1635
1$
1+
1*
b11 !
b11 &
1)
1"
#1640
0"
#1645
0$
0%
0+
0*
0)
0,
b100 !
b100 &
1-
1"
#1650
0"
#1655
1+
1*
b101 !
b101 &
1)
1"
#1660
0"
#1665
0+
0*
0)
b110 !
b110 &
1,
1"
#1670
0"
#1675
1%
1$
1+
1*
b111 !
b111 &
1)
1"
#1680
0"
#1685
0$
0%
0+
0*
0)
0,
0-
b1000 !
b1000 &
1.
1"
#1690
0"
#1695
1+
1*
b1001 !
b1001 &
1)
1"
#1700
0"
#1705
0+
0*
0)
b1010 !
b1010 &
1,
1"
#1710
0"
#1715
1$
1+
1*
b1011 !
b1011 &
1)
1"
#1720
0"
#1725
0$
0%
0+
0*
0)
0,
b1100 !
b1100 &
1-
1"
#1730
0"
#1735
1+
1*
b1101 !
b1101 &
1)
1"
#1740
0"
#1745
0+
0*
0)
b1110 !
b1110 &
1,
1"
#1750
0"
#1755
1%
1$
1+
1*
b1111 !
b1111 &
1)
1"
#1760
0"
#1765
0$
0%
0+
0*
0)
0,
0-
b0 !
b0 &
0.
1"
#1770
0"
#1775
1+
1*
b1 !
b1 &
1)
1"
#1780
0"
#1785
0+
0*
0)
b10 !
b10 &
1,
1"
#1790
0"
#1795
1$
1+
1*
b11 !
b11 &
1)
1"
#1800
0"
#1805
0$
0%
0+
0*
0)
0,
b100 !
b100 &
1-
1"
#1810
0"
#1815
1+
1*
b101 !
b101 &
1)
1"
#1820
0"
#1825
0+
0*
0)
b110 !
b110 &
1,
1"
#1830
0"
#1835
1%
1$
1+
1*
b111 !
b111 &
1)
1"
#1840
0"
#1845
0$
0%
0+
0*
0)
0,
0-
b1000 !
b1000 &
1.
1"
#1850
0"
#1855
1+
1*
b1001 !
b1001 &
1)
1"
#1860
0"
#1865
0+
0*
0)
b1010 !
b1010 &
1,
1"
#1870
0"
#1875
1$
1+
1*
b1011 !
b1011 &
1)
1"
#1880
0"
#1885
0$
0%
0+
0*
0)
0,
b1100 !
b1100 &
1-
1"
#1890
0"
#1895
1+
1*
b1101 !
b1101 &
1)
1"
#1900
0"
#1905
0+
0*
0)
b1110 !
b1110 &
1,
1"
#1910
0"
#1915
1%
1$
1+
1*
b1111 !
b1111 &
1)
1"
#1920
0"
#1925
0$
0%
0+
0*
0)
0,
0-
b0 !
b0 &
0.
1"
#1930
0"
#1935
1+
1*
b1 !
b1 &
1)
1"
#1940
0"
#1945
0+
0*
0)
b10 !
b10 &
1,
1"
#1950
0"
#1955
1$
1+
1*
b11 !
b11 &
1)
1"
#1960
0"
#1965
0$
0%
0+
0*
0)
0,
b100 !
b100 &
1-
1"
#1970
0"
#1975
1+
1*
b101 !
b101 &
1)
1"
#1980
0"
#1985
0+
0*
0)
b110 !
b110 &
1,
1"
#1990
0"
#1995
1%
1$
1+
1*
b111 !
b111 &
1)
1"
#2000
0"
#2005
0$
0%
0+
0*
0)
0,
0-
b1000 !
b1000 &
1.
1"
#2010
0"
#2015
1+
1*
b1001 !
b1001 &
1)
1"
#2020
0"
#2025
0+
0*
0)
b1010 !
b1010 &
1,
1"
#2030
0"
#2035
1$
1+
1*
b1011 !
b1011 &
1)
1"
#2040
0"
#2045
0$
0%
0+
0*
0)
0,
b1100 !
b1100 &
1-
1"
#2050
0"
#2055
1+
1*
b1101 !
b1101 &
1)
1"
#2060
0"
#2065
0+
0*
0)
b1110 !
b1110 &
1,
1"
#2070
0"
#2075
1%
1$
1+
1*
b1111 !
b1111 &
1)
1"
#2080
0"
#2085
0$
0%
0+
0*
0)
0,
0-
b0 !
b0 &
0.
1"
#2090
0"
#2095
1+
1*
b1 !
b1 &
1)
1"
#2100
0"
#2105
0+
0*
0)
b10 !
b10 &
1,
1"
#2110
0"
#2115
1$
1+
1*
b11 !
b11 &
1)
1"
#2120
0"
#2125
0$
0%
0+
0*
0)
0,
b100 !
b100 &
1-
1"
#2130
0"
#2135
1+
1*
b101 !
b101 &
1)
1"
#2140
0"
#2145
0+
0*
0)
b110 !
b110 &
1,
1"
#2150
0"
#2155
1%
1$
1+
1*
b111 !
b111 &
1)
1"
#2160
0"
#2165
0$
0%
0+
0*
0)
0,
0-
b1000 !
b1000 &
1.
1"
#2170
0"
#2175
1+
1*
b1001 !
b1001 &
1)
1"
#2180
0"
#2185
0+
0*
0)
b1010 !
b1010 &
1,
1"
#2190
0"
#2195
1$
1+
1*
b1011 !
b1011 &
1)
1"
#2200
0"
#2205
0$
0%
0+
0*
0)
0,
b1100 !
b1100 &
1-
1"
#2210
0"
#2215
1+
1*
b1101 !
b1101 &
1)
1"
#2220
0"
#2225
0+
0*
0)
b1110 !
b1110 &
1,
1"
#2230
0"
#2235
1%
1$
1+
1*
b1111 !
b1111 &
1)
1"
#2240
0"
#2245
0$
0%
0+
0*
0)
0,
0-
b0 !
b0 &
0.
1"
#2250
0"
#2255
1+
1*
b1 !
b1 &
1)
1"
#2260
0"
#2265
0+
0*
0)
b10 !
b10 &
1,
1"
#2270
0"
#2275
1$
1+
1*
b11 !
b11 &
1)
1"
#2280
0"
#2285
0$
0%
0+
0*
0)
0,
b100 !
b100 &
1-
1"
#2290
0"
#2295
1+
1*
b101 !
b101 &
1)
1"
#2300
0"
#2305
0+
0*
0)
b110 !
b110 &
1,
1"
#2310
0"
#2315
1%
1$
1+
1*
b111 !
b111 &
1)
1"
#2320
0"
#2325
0$
0%
0+
0*
0)
0,
0-
b1000 !
b1000 &
1.
1"
#2330
0"
#2335
1+
1*
b1001 !
b1001 &
1)
1"
#2340
0"
#2345
0+
0*
0)
b1010 !
b1010 &
1,
1"
#2350
0"
#2355
1$
1+
1*
b1011 !
b1011 &
1)
1"
#2360
0"
#2365
0$
0%
0+
0*
0)
0,
b1100 !
b1100 &
1-
1"
#2370
0"
#2375
1+
1*
b1101 !
b1101 &
1)
1"
#2380
0"
#2385
0+
0*
0)
b1110 !
b1110 &
1,
1"
#2390
0"
#2395
1%
1$
1+
1*
b1111 !
b1111 &
1)
1"
#2400
0"
#2405
0$
0%
0+
0*
0)
0,
0-
b0 !
b0 &
0.
1"
#2410
0"
#2415
1+
1*
b1 !
b1 &
1)
1"
#2420
0"
#2425
0+
0*
0)
b10 !
b10 &
1,
1"
#2430
0"
#2435
1$
1+
1*
b11 !
b11 &
1)
1"
#2440
0"
#2445
0$
0%
0+
0*
0)
0,
b100 !
b100 &
1-
1"
#2450
0"
#2455
1+
1*
b101 !
b101 &
1)
1"
#2460
0"
#2465
0+
0*
0)
b110 !
b110 &
1,
1"
#2470
0"
#2475
1%
1$
1+
1*
b111 !
b111 &
1)
1"
#2480
0"
#2485
0$
0%
0+
0*
0)
0,
0-
b1000 !
b1000 &
1.
1"
#2490
0"
#2495
1+
1*
b1001 !
b1001 &
1)
1"
#2500
0"
#2505
0+
0*
0)
b1010 !
b1010 &
1,
1"
#2510
0"
#2515
1$
1+
1*
b1011 !
b1011 &
1)
1"
#2520
0"
#2525
0$
0%
0+
0*
0)
0,
b1100 !
b1100 &
1-
1"
#2530
0"
#2535
1+
1*
b1101 !
b1101 &
1)
1"
#2540
0"
#2545
0+
0*
0)
b1110 !
b1110 &
1,
1"
#2550
0"
#2555
1%
1$
1+
1*
b1111 !
b1111 &
1)
1"
#2560
0"
#2565
0$
0%
0+
0*
0)
0,
0-
b0 !
b0 &
0.
1"
#2570
0"
#2575
1+
1*
b1 !
b1 &
1)
1"
#2580
0"
#2585
0+
0*
0)
b10 !
b10 &
1,
1"
#2590
0"
#2595
1$
1+
1*
b11 !
b11 &
1)
1"
#2600
0"
#2605
0$
0%
0+
0*
0)
0,
b100 !
b100 &
1-
1"
#2610
0"
#2615
1+
1*
b101 !
b101 &
1)
1"
#2620
0"
#2625
0+
0*
0)
b110 !
b110 &
1,
1"
#2630
0"
#2635
1%
1$
1+
1*
b111 !
b111 &
1)
1"
#2640
0"
#2645
0$
0%
0+
0*
0)
0,
0-
b1000 !
b1000 &
1.
1"
#2650
0"
#2655
1+
1*
b1001 !
b1001 &
1)
1"
#2660
0"
#2665
0+
0*
0)
b1010 !
b1010 &
1,
1"
#2670
0"
#2675
1$
1+
1*
b1011 !
b1011 &
1)
1"
#2680
0"
#2685
0$
0%
0+
0*
0)
0,
b1100 !
b1100 &
1-
1"
#2690
0"
#2695
1+
1*
b1101 !
b1101 &
1)
1"
#2700
0"
#2705
0+
0*
0)
b1110 !
b1110 &
1,
1"
#2710
0"
#2715
1%
1$
1+
1*
b1111 !
b1111 &
1)
1"
#2720
0"
#2725
0$
0%
0+
0*
0)
0,
0-
b0 !
b0 &
0.
1"
#2730
0"
#2735
1+
1*
b1 !
b1 &
1)
1"
#2740
0"
#2745
0+
0*
0)
b10 !
b10 &
1,
1"
#2750
0"
#2755
1$
1+
1*
b11 !
b11 &
1)
1"
#2760
0"
#2765
0$
0%
0+
0*
0)
0,
b100 !
b100 &
1-
1"
#2770
0"
#2775
1+
1*
b101 !
b101 &
1)
1"
#2780
0"
#2785
0+
0*
0)
b110 !
b110 &
1,
1"
#2790
0"
#2795
1%
1$
1+
1*
b111 !
b111 &
1)
1"
#2800
0"
#2805
0$
0%
0+
0*
0)
0,
0-
b1000 !
b1000 &
1.
1"
#2810
0"
#2815
1+
1*
b1001 !
b1001 &
1)
1"
#2820
0"
#2825
0+
0*
0)
b1010 !
b1010 &
1,
1"
#2830
0"
#2835
1$
1+
1*
b1011 !
b1011 &
1)
1"
#2840
0"
#2845
0$
0%
0+
0*
0)
0,
b1100 !
b1100 &
1-
1"
#2850
0"
#2855
1+
1*
b1101 !
b1101 &
1)
1"
#2860
0"
#2865
0+
0*
0)
b1110 !
b1110 &
1,
1"
#2870
0"
#2875
1%
1$
1+
1*
b1111 !
b1111 &
1)
1"
#2880
0"
#2885
0$
0%
0+
0*
0)
0,
0-
b0 !
b0 &
0.
1"
#2890
0"
#2895
1+
1*
b1 !
b1 &
1)
1"
#2900
0"
#2905
0+
0*
0)
b10 !
b10 &
1,
1"
#2910
0"
#2915
1$
1+
1*
b11 !
b11 &
1)
1"
#2920
0"
#2925
0$
0%
0+
0*
0)
0,
b100 !
b100 &
1-
1"
#2930
0"
#2935
1+
1*
b101 !
b101 &
1)
1"
#2940
0"
#2945
0+
0*
0)
b110 !
b110 &
1,
1"
#2950
0"
#2955
1%
1$
1+
1*
b111 !
b111 &
1)
1"
#2960
0"
#2965
0$
0%
0+
0*
0)
0,
0-
b1000 !
b1000 &
1.
1"
#2970
0"
#2975
1+
1*
b1001 !
b1001 &
1)
1"
#2980
0"
#2985
0+
0*
0)
b1010 !
b1010 &
1,
1"
#2990
0"
#2995
1$
1+
1*
b1011 !
b1011 &
1)
1"
#3000
0"
#3005
0$
0%
0+
0*
0)
0,
b1100 !
b1100 &
1-
1"
#3010
0"
#3015
1+
1*
b1101 !
b1101 &
1)
1"
#3020
0"
#3025
0+
0*
0)
b1110 !
b1110 &
1,
1"
#3030
0"
#3035
1%
1$
1+
1*
b1111 !
b1111 &
1)
1"
#3040
0"
#3045
0$
0%
0+
0*
0)
0,
0-
b0 !
b0 &
0.
1"
#3050
0"
#3055
1+
1*
b1 !
b1 &
1)
1"
#3060
0"
#3065
0+
0*
0)
b10 !
b10 &
1,
1"
#3070
0"
#3075
1$
1+
1*
b11 !
b11 &
1)
1"
#3080
0"
#3085
0$
0%
0+
0*
0)
0,
b100 !
b100 &
1-
1"
#3090
0"
#3095
1+
1*
b101 !
b101 &
1)
1"
#3100
0"
#3105
0+
0*
0)
b110 !
b110 &
1,
1"
#3110
0"
#3115
1%
1$
1+
1*
b111 !
b111 &
1)
1"
#3120
0"
#3125
0$
0%
0+
0*
0)
0,
0-
b1000 !
b1000 &
1.
1"
#3130
0"
#3135
1+
1*
b1001 !
b1001 &
1)
1"
#3140
0"
#3145
0+
0*
0)
b1010 !
b1010 &
1,
1"
#3150
0"
#3155
1$
1+
1*
b1011 !
b1011 &
1)
1"
#3160
0"
#3165
0$
0%
0+
0*
0)
0,
b1100 !
b1100 &
1-
1"
#3170
0"
#3175
1+
1*
b1101 !
b1101 &
1)
1"
#3180
0"
#3185
0+
0*
0)
b1110 !
b1110 &
1,
1"
#3190
0"
#3195
1%
1$
1+
1*
b1111 !
b1111 &
1)
1"
#3200
0"
#3205
0$
0%
0+
0*
0)
0,
0-
b0 !
b0 &
0.
1"
#3210
0"
#3215
1+
1*
b1 !
b1 &
1)
1"
#3220
0"
#3225
0+
0*
0)
b10 !
b10 &
1,
1"
#3230
0"
#3235
1$
1+
1*
b11 !
b11 &
1)
1"
#3240
0"
#3245
0$
0%
0+
0*
0)
0,
b100 !
b100 &
1-
1"
#3250
0"
#3255
1+
1*
b101 !
b101 &
1)
1"
#3260
0"
#3265
0+
0*
0)
b110 !
b110 &
1,
1"
#3270
0"
#3275
1%
1$
1+
1*
b111 !
b111 &
1)
1"
#3280
0"
#3285
0$
0%
0+
0*
0)
0,
0-
b1000 !
b1000 &
1.
1"
#3290
0"
#3295
1+
1*
b1001 !
b1001 &
1)
1"
#3300
0"
#3305
0+
0*
0)
b1010 !
b1010 &
1,
1"
#3310
0"
#3315
1$
1+
1*
b1011 !
b1011 &
1)
1"
#3320
0"
#3325
0$
0%
0+
0*
0)
0,
b1100 !
b1100 &
1-
1"
#3330
0"
#3335
1+
1*
b1101 !
b1101 &
1)
1"
#3340
0"
#3345
0+
0*
0)
b1110 !
b1110 &
1,
1"
#3350
0"
#3355
1%
1$
1+
1*
b1111 !
b1111 &
1)
1"
#3360
0"
#3365
0$
0%
0+
0*
0)
0,
0-
b0 !
b0 &
0.
1"
#3370
0"
#3375
1+
1*
b1 !
b1 &
1)
1"
#3380
0"
#3385
0+
0*
0)
b10 !
b10 &
1,
1"
#3390
0"
#3395
1$
1+
1*
b11 !
b11 &
1)
1"
#3400
0"
#3405
0$
0%
0+
0*
0)
0,
b100 !
b100 &
1-
1"
#3410
0"
#3415
1+
1*
b101 !
b101 &
1)
1"
#3420
0"
#3425
0+
0*
0)
b110 !
b110 &
1,
1"
#3430
0"
#3435
1%
1$
1+
1*
b111 !
b111 &
1)
1"
#3440
0"
#3445
0$
0%
0+
0*
0)
0,
0-
b1000 !
b1000 &
1.
1"
#3450
0"
#3455
1+
1*
b1001 !
b1001 &
1)
1"
#3460
0"
#3465
0+
0*
0)
b1010 !
b1010 &
1,
1"
#3470
0"
#3475
1$
1+
1*
b1011 !
b1011 &
1)
1"
#3480
0"
#3485
0$
0%
0+
0*
0)
0,
b1100 !
b1100 &
1-
1"
#3490
0"
#3495
1+
1*
b1101 !
b1101 &
1)
1"
#3500
0"
#3505
0+
0*
0)
b1110 !
b1110 &
1,
1"
#3510
0"
#3515
1%
1$
1+
1*
b1111 !
b1111 &
1)
1"
#3520
0"
#3525
0$
0%
0+
0*
0)
0,
0-
b0 !
b0 &
0.
1"
#3530
0"
#3535
1+
1*
b1 !
b1 &
1)
1"
#3540
0"
